grammarie/__init__.py
grammarie/types.py
grammarie-0.1.1.dist-info/LICENSE
grammarie-0.1.1.dist-info/METADATA
grammarie-0.1.1.dist-info/WHEEL
grammarie-0.1.1.dist-info/RECORD
