Metadata-Version: 2.1
Name: grammarie
Version: 0.1.1
Summary: Custom Pydantic types and validators
Home-page: https://gitlab.statnett.no//grammarie.git
Keywords: pydantic,types,validation,coercion,annotated
Author: Statnett Datascience
Author-email: Datascience.Drift@Statnett.no
Requires-Python: >=3.10,<4.0
Classifier: Intended Audience :: Developers
Classifier: License :: OSI Approved :: MIT License
Classifier: Programming Language :: Python :: 3
Classifier: Programming Language :: Python :: 3.10
Classifier: Programming Language :: Python :: 3.11
Classifier: Programming Language :: Python :: 3.12
Classifier: Programming Language :: Python :: Implementation :: CPython
Classifier: Topic :: Software Development :: Libraries :: Python Modules
Requires-Dist: pydantic (>=2.2.0)
Project-URL: Repository, https://gitlab.statnett.no//grammarie.git
